frackture/__init__.py
frackture-0.1.0.dist-info/METADATA
frackture-0.1.0.dist-info/WHEEL
frackture-0.1.0.dist-info/top_level.txt
frackture-0.1.0.dist-info/RECORD
