Metadata-Version: 2.4
Name: frackture
Version: 0.1.0
Summary: Frackture is a symbolic compression engine using recursive logic and entropy patterns.
Author: GoryGrey
Classifier: Programming Language :: Python :: 3
Classifier: License :: OSI Approved :: MIT License
Classifier: Operating System :: OS Independent
Requires-Python: >=3.8
Requires-Dist: numpy
Requires-Dist: scipy
Requires-Dist: scikit-learn
Dynamic: author
Dynamic: classifier
Dynamic: description
Dynamic: description-content-type
Dynamic: requires-dist
Dynamic: requires-python
Dynamic: summary
